ModCog/__init__.py
ModCog/setup.py
ModCog-0.0.1.dist-info/METADATA
ModCog-0.0.1.dist-info/WHEEL
ModCog-0.0.1.dist-info/top_level.txt
ModCog-0.0.1.dist-info/RECORD
